LICENSE.txt
MANIFEST.in
README.rst
setup.py
aperturesynth/__init__.py
aperturesynth/gui.py
aperturesynth/register.py
aperturesynth/synthesise.py
aperturesynth.egg-info/PKG-INFO
aperturesynth.egg-info/SOURCES.txt
aperturesynth.egg-info/dependency_links.txt
aperturesynth.egg-info/entry_points.txt
aperturesynth.egg-info/requires.txt
aperturesynth.egg-info/top_level.txt