Metadata-Version: 1.1
Name: aperturesynth
Version: 0.0.1
Summary: A tool for registering and combining series of handheld photographs
Home-page: https://github.com/SamHames/aperturesynth
Author: Sam Hames
Author-email: samuel.hames@uqconnect.edu.au
License: MIT
Keywords: photography processing synthesis
Platform: UNKNOWN
Classifier: Development Status :: 3 - Alpha
Classifier: Intended Audience :: End Users/Desktop
Classifier: Topic :: Multimedia :: Graphics
Classifier: Topic :: Artistic Software
Classifier: License :: OSI Approved :: MIT License
Classifier: Programming Language :: Python :: 2
Classifier: Programming Language :: Python :: 2.7
Classifier: Programming Language :: Python :: 3
